setup.py
bindtools/__init__.py
bindtools/check_zone.py
bindtools/reload_zone.py
python_bindtools.egg-info/PKG-INFO
python_bindtools.egg-info/SOURCES.txt
python_bindtools.egg-info/dependency_links.txt
python_bindtools.egg-info/pbr.json
python_bindtools.egg-info/top_level.txt