Metadata-Version: 1.1
Name: python-bindtools
Version: 0.1.4
Summary: A wrapper for binds DNS tools
Home-page: https://github.com/scgodbold/zoner
Author: Scott Godbold
Author-email: scott@gmail.com
License: MIT
Keywords: dns rndc zone named bind
Platform: UNKNOWN
Classifier: Development Status :: 3 - Alpha
Classifier: Intended Audience :: Developers
Classifier: License :: OSI Approved :: MIT License
Classifier: Programming Language :: Python :: 2.7
Classifier: Programming Language :: Python :: 3
Classifier: Programming Language :: Python :: 3.4
